inoc_reporter/__init__.py
shared_code/__init__.py
shared_code/connectDB.py
shared_code/createtable.py
shared_code/inoc_automator.py
inoc_module-1.0.0.dist-info/METADATA
inoc_module-1.0.0.dist-info/WHEEL
inoc_module-1.0.0.dist-info/top_level.txt
inoc_module-1.0.0.dist-info/RECORD
